uonet_fslogin/__init__.py
uonet_fslogin/errors.py
uonet_fslogin/main.py
uonet_fslogin/utils.py
uonet_fslogin-0.2.0.dist-info/LICENSE
uonet_fslogin-0.2.0.dist-info/METADATA
uonet_fslogin-0.2.0.dist-info/WHEEL
uonet_fslogin-0.2.0.dist-info/top_level.txt
uonet_fslogin-0.2.0.dist-info/RECORD
